Metadata-Version: 2.1
Name: clickhousepy
Version: 2020.10.4
Summary: Python обертка для запросов в БД Clickhouse
Home-page: https://github.com/pavelmaksimov/clickhousepy
Author: Pavel Maksimov
Author-email: vur21@ya.ru
License: MIT
Keywords: clickhouse,python,wrapper
Platform: UNKNOWN
Provides-Extra: pandas
